Metadata-Version: 1.0
Name: dl20211
Version: 1.1
Summary: Test Hello
Home-page: UNKNOWN
Author: AlbertLi
Author-email: 1850801419@qq.com
License: Li
Platform: UNKNOWN
